{
  "uid": "Xunit.Sdk.IXunitSerializer",
  "isEii": false,
  "isExtensionMethod": false,
  "parent": {
    "uid": "Xunit.Sdk",
    "isEii": false,
    "isExtensionMethod": false,
    "href": "Xunit.html",
    "name": [
      {
        "lang": "csharp",
        "value": "Xunit.Sdk"
      },
      {
        "lang": "vb",
        "value": "Xunit.Sdk"
      }
    ],
    "nameWithType": [
      {
        "lang": "csharp",
        "value": "Xunit.Sdk"
      },
      {
        "lang": "vb",
        "value": "Xunit.Sdk"
      }
    ],
    "fullName": [
      {
        "lang": "csharp",
        "value": "Xunit.Sdk"
      },
      {
        "lang": "vb",
        "value": "Xunit.Sdk"
      }
    ],
    "specName": [
      {
        "lang": "csharp",
        "value": "<a class=\"xref\" href=\"Xunit.html\">Xunit</a>.<a class=\"xref\" href=\"Xunit.Sdk.html\">Sdk</a>"
      },
      {
        "lang": "vb",
        "value": "<a class=\"xref\" href=\"Xunit.html\">Xunit</a>.<a class=\"xref\" href=\"Xunit.Sdk.html\">Sdk</a>"
      }
    ],
    "level": 0
  },
  "children": [
    {
      "uid": "Xunit.Sdk.IXunitSerializer.Deserialize(System.Type,System.String)",
      "isEii": false,
      "isExtensionMethod": false,
      "parent": "Xunit.Sdk.IXunitSerializer",
      "isExternal": false,
      "name": [
        {
          "lang": "csharp",
          "value": "Deserialize(Type, string)"
        },
        {
          "lang": "vb",
          "value": "Deserialize(Type, String)"
        }
      ],
      "nameWithType": [
        {
          "lang": "csharp",
          "value": "IXunitSerializer.Deserialize(Type, string)"
        },
        {
          "lang": "vb",
          "value": "IXunitSerializer.Deserialize(Type, String)"
        }
      ],
      "fullName": [
        {
          "lang": "csharp",
          "value": "Xunit.Sdk.IXunitSerializer.Deserialize(System.Type, string)"
        },
        {
          "lang": "vb",
          "value": "Xunit.Sdk.IXunitSerializer.Deserialize(System.Type, String)"
        }
      ],
      "specName": [
        {
          "lang": "csharp",
          "value": "<xref uid=\"Xunit.Sdk.IXunitSerializer.Deserialize(System.Type,System.String)\" text=\"Deserialize(Type, string)\"/>"
        },
        {
          "lang": "vb",
          "value": "<xref uid=\"Xunit.Sdk.IXunitSerializer.Deserialize(System.Type,System.String)\" text=\"Deserialize(Type, string)\"/>"
        }
      ],
      "syntax": {
        "content": [
          {
            "lang": "csharp",
            "value": "object Deserialize(Type type, string serializedValue)"
          },
          {
            "lang": "vb",
            "value": "Function Deserialize(type As Type, serializedValue As String) As Object"
          }
        ],
        "parameters": [
          {
            "id": "type",
            "type": {
              "uid": "System.Type",
              "name": [
                {
                  "lang": "csharp",
                  "value": "Type"
                },
                {
                  "lang": "vb",
                  "value": "Type"
                }
              ],
              "nameWithType": [
                {
                  "lang": "csharp",
                  "value": "Type"
                },
                {
                  "lang": "vb",
                  "value": "Type"
                }
              ],
              "fullName": [
                {
                  "lang": "csharp",
                  "value": "System.Type"
                },
                {
                  "lang": "vb",
                  "value": "System.Type"
                }
              ],
              "specName": [
                {
                  "lang": "csharp",
                  "value": "<xref uid=\"System.Type\" text=\"Type\"/>"
                },
                {
                  "lang": "vb",
                  "value": "<xref uid=\"System.Type\" text=\"Type\"/>"
                }
              ]
            },
            "description": "<p sourcefile=\"v3-2.0.0/common/Xunit.Sdk.IXunitSerializer.yml\" sourcestartlinenumber=\"1\">The type of the original value</p>\n"
          },
          {
            "id": "serializedValue",
            "type": {
              "uid": "System.String",
              "name": [
                {
                  "lang": "csharp",
                  "value": "string"
                },
                {
                  "lang": "vb",
                  "value": "String"
                }
              ],
              "nameWithType": [
                {
                  "lang": "csharp",
                  "value": "string"
                },
                {
                  "lang": "vb",
                  "value": "String"
                }
              ],
              "fullName": [
                {
                  "lang": "csharp",
                  "value": "string"
                },
                {
                  "lang": "vb",
                  "value": "String"
                }
              ],
              "specName": [
                {
                  "lang": "csharp",
                  "value": "<xref uid=\"System.String\" text=\"string\"/>"
                },
                {
                  "lang": "vb",
                  "value": "<xref uid=\"System.String\" text=\"string\"/>"
                }
              ]
            },
            "description": "<p sourcefile=\"v3-2.0.0/common/Xunit.Sdk.IXunitSerializer.yml\" sourcestartlinenumber=\"1\">The serialized value</p>\n"
          }
        ],
        "return": {
          "type": {
            "uid": "System.Object",
            "name": [
              {
                "lang": "csharp",
                "value": "object"
              },
              {
                "lang": "vb",
                "value": "Object"
              }
            ],
            "nameWithType": [
              {
                "lang": "csharp",
                "value": "object"
              },
              {
                "lang": "vb",
                "value": "Object"
              }
            ],
            "fullName": [
              {
                "lang": "csharp",
                "value": "object"
              },
              {
                "lang": "vb",
                "value": "Object"
              }
            ],
            "specName": [
              {
                "lang": "csharp",
                "value": "<xref uid=\"System.Object\" text=\"object\"/>"
              },
              {
                "lang": "vb",
                "value": "<xref uid=\"System.Object\" text=\"object\"/>"
              }
            ]
          },
          "description": "<p sourcefile=\"v3-2.0.0/common/Xunit.Sdk.IXunitSerializer.yml\" sourcestartlinenumber=\"1\">The deserialized value</p>\n"
        }
      },
      "source": {
        "remote": {
          "path": "src/xunit.v3.common/Abstractions/Serialization/IXunitSerializer.cs",
          "branch": "229879b7653ec0573f36ca4759ccfc915be11a21",
          "repo": "https://github.com/xunit/xunit.git"
        },
        "id": "Deserialize",
        "path": "../v3/v3-2.0.0/src/xunit.v3.common/Abstractions/Serialization/IXunitSerializer.cs",
        "startLine": 18,
        "endLine": 0
      },
      "assemblies": [
        "xunit.v3.common"
      ],
      "namespace": "Xunit.Sdk",
      "example": [],
      "overload": {
        "uid": "Xunit.Sdk.IXunitSerializer.Deserialize*",
        "name": [
          {
            "lang": "csharp",
            "value": "Deserialize"
          },
          {
            "lang": "vb",
            "value": "Deserialize"
          }
        ],
        "nameWithType": [
          {
            "lang": "csharp",
            "value": "IXunitSerializer.Deserialize"
          },
          {
            "lang": "vb",
            "value": "IXunitSerializer.Deserialize"
          }
        ],
        "fullName": [
          {
            "lang": "csharp",
            "value": "Xunit.Sdk.IXunitSerializer.Deserialize"
          },
          {
            "lang": "vb",
            "value": "Xunit.Sdk.IXunitSerializer.Deserialize"
          }
        ],
        "specName": [
          {
            "lang": "csharp",
            "value": "<xref uid=\"Xunit.Sdk.IXunitSerializer.Deserialize*\" text=\"Deserialize\"/>"
          },
          {
            "lang": "vb",
            "value": "<xref uid=\"Xunit.Sdk.IXunitSerializer.Deserialize*\" text=\"Deserialize\"/>"
          }
        ]
      },
      "level": 0,
      "type": "method",
      "summary": "<p sourcefile=\"v3-2.0.0/common/Xunit.Sdk.IXunitSerializer.yml\" sourcestartlinenumber=\"1\">Deserializes a value that was obtained from <xref href=\"Xunit.Sdk.IXunitSerializer.Serialize(System.Object)\" data-throw-if-not-resolved=\"false\"></xref>.</p>\n",
      "platform": null
    },
    {
      "uid": "Xunit.Sdk.IXunitSerializer.IsSerializable(System.Type,System.Object,System.String@)",
      "isEii": false,
      "isExtensionMethod": false,
      "parent": "Xunit.Sdk.IXunitSerializer",
      "isExternal": false,
      "name": [
        {
          "lang": "csharp",
          "value": "IsSerializable(Type, object?, out string?)"
        },
        {
          "lang": "vb",
          "value": "IsSerializable(Type, Object, String)"
        }
      ],
      "nameWithType": [
        {
          "lang": "csharp",
          "value": "IXunitSerializer.IsSerializable(Type, object?, out string?)"
        },
        {
          "lang": "vb",
          "value": "IXunitSerializer.IsSerializable(Type, Object, String)"
        }
      ],
      "fullName": [
        {
          "lang": "csharp",
          "value": "Xunit.Sdk.IXunitSerializer.IsSerializable(System.Type, object?, out string?)"
        },
        {
          "lang": "vb",
          "value": "Xunit.Sdk.IXunitSerializer.IsSerializable(System.Type, Object, String)"
        }
      ],
      "specName": [
        {
          "lang": "csharp",
          "value": "<xref uid=\"Xunit.Sdk.IXunitSerializer.IsSerializable(System.Type,System.Object,System.String@)\" text=\"IsSerializable(Type, object?, out string?)\"/>"
        },
        {
          "lang": "vb",
          "value": "<xref uid=\"Xunit.Sdk.IXunitSerializer.IsSerializable(System.Type,System.Object,System.String@)\" text=\"IsSerializable(Type, object?, out string?)\"/>"
        }
      ],
      "syntax": {
        "content": [
          {
            "lang": "csharp",
            "value": "bool IsSerializable(Type type, object? value, out string? failureReason)"
          },
          {
            "lang": "vb",
            "value": "Function IsSerializable(type As Type, value As Object, failureReason As String) As Boolean"
          }
        ],
        "parameters": [
          {
            "id": "type",
            "type": {
              "uid": "System.Type",
              "name": [
                {
                  "lang": "csharp",
                  "value": "Type"
                },
                {
                  "lang": "vb",
                  "value": "Type"
                }
              ],
              "nameWithType": [
                {
                  "lang": "csharp",
                  "value": "Type"
                },
                {
                  "lang": "vb",
                  "value": "Type"
                }
              ],
              "fullName": [
                {
                  "lang": "csharp",
                  "value": "System.Type"
                },
                {
                  "lang": "vb",
                  "value": "System.Type"
                }
              ],
              "specName": [
                {
                  "lang": "csharp",
                  "value": "<xref uid=\"System.Type\" text=\"Type\"/>"
                },
                {
                  "lang": "vb",
                  "value": "<xref uid=\"System.Type\" text=\"Type\"/>"
                }
              ]
            },
            "description": "<p sourcefile=\"v3-2.0.0/common/Xunit.Sdk.IXunitSerializer.yml\" sourcestartlinenumber=\"1\">The type of the value</p>\n"
          },
          {
            "id": "value",
            "type": {
              "uid": "System.Object",
              "name": [
                {
                  "lang": "csharp",
                  "value": "object"
                },
                {
                  "lang": "vb",
                  "value": "Object"
                }
              ],
              "nameWithType": [
                {
                  "lang": "csharp",
                  "value": "object"
                },
                {
                  "lang": "vb",
                  "value": "Object"
                }
              ],
              "fullName": [
                {
                  "lang": "csharp",
                  "value": "object"
                },
                {
                  "lang": "vb",
                  "value": "Object"
                }
              ],
              "specName": [
                {
                  "lang": "csharp",
                  "value": "<xref uid=\"System.Object\" text=\"object\"/>"
                },
                {
                  "lang": "vb",
                  "value": "<xref uid=\"System.Object\" text=\"object\"/>"
                }
              ]
            },
            "description": "<p sourcefile=\"v3-2.0.0/common/Xunit.Sdk.IXunitSerializer.yml\" sourcestartlinenumber=\"1\">The value to test</p>\n"
          },
          {
            "id": "failureReason",
            "type": {
              "uid": "System.String",
              "name": [
                {
                  "lang": "csharp",
                  "value": "string"
                },
                {
                  "lang": "vb",
                  "value": "String"
                }
              ],
              "nameWithType": [
                {
                  "lang": "csharp",
                  "value": "string"
                },
                {
                  "lang": "vb",
                  "value": "String"
                }
              ],
              "fullName": [
                {
                  "lang": "csharp",
                  "value": "string"
                },
                {
                  "lang": "vb",
                  "value": "String"
                }
              ],
              "specName": [
                {
                  "lang": "csharp",
                  "value": "<xref uid=\"System.String\" text=\"string\"/>"
                },
                {
                  "lang": "vb",
                  "value": "<xref uid=\"System.String\" text=\"string\"/>"
                }
              ]
            },
            "description": "<p sourcefile=\"v3-2.0.0/common/Xunit.Sdk.IXunitSerializer.yml\" sourcestartlinenumber=\"1\">Returns a failure reason when the value isn't serializable</p>\n"
          }
        ],
        "return": {
          "type": {
            "uid": "System.Boolean",
            "name": [
              {
                "lang": "csharp",
                "value": "bool"
              },
              {
                "lang": "vb",
                "value": "Boolean"
              }
            ],
            "nameWithType": [
              {
                "lang": "csharp",
                "value": "bool"
              },
              {
                "lang": "vb",
                "value": "Boolean"
              }
            ],
            "fullName": [
              {
                "lang": "csharp",
                "value": "bool"
              },
              {
                "lang": "vb",
                "value": "Boolean"
              }
            ],
            "specName": [
              {
                "lang": "csharp",
                "value": "<xref uid=\"System.Boolean\" text=\"bool\"/>"
              },
              {
                "lang": "vb",
                "value": "<xref uid=\"System.Boolean\" text=\"bool\"/>"
              }
            ]
          },
          "description": "<p sourcefile=\"v3-2.0.0/common/Xunit.Sdk.IXunitSerializer.yml\" sourcestartlinenumber=\"1\">Return <code>true</code> if the value is serializable; <code>false</code>, otherwise</p>\n"
        }
      },
      "source": {
        "remote": {
          "path": "src/xunit.v3.common/Abstractions/Serialization/IXunitSerializer.cs",
          "branch": "229879b7653ec0573f36ca4759ccfc915be11a21",
          "repo": "https://github.com/xunit/xunit.git"
        },
        "id": "IsSerializable",
        "path": "../v3/v3-2.0.0/src/xunit.v3.common/Abstractions/Serialization/IXunitSerializer.cs",
        "startLine": 40,
        "endLine": 0
      },
      "assemblies": [
        "xunit.v3.common"
      ],
      "namespace": "Xunit.Sdk",
      "remarks": "<p sourcefile=\"v3-2.0.0/common/Xunit.Sdk.IXunitSerializer.yml\" sourcestartlinenumber=\"1\">This will be called by <xref href=\"Xunit.Sdk.SerializationHelper.IsSerializable(System.Object)\" data-throw-if-not-resolved=\"false\"></xref>,\n<xref href=\"Xunit.Sdk.SerializationHelper.IsSerializable(System.Object%2cSystem.Type)\" data-throw-if-not-resolved=\"false\"></xref>, and\n<xref href=\"Xunit.Sdk.SerializationHelper.Serialize(System.Object%2cSystem.Type)\" data-throw-if-not-resolved=\"false\"></xref>. The failure reason is used when\ncalled from <code>Serialize</code> to format an error exception, but is otherwise ignored\nfrom the calls from <code>IsSerializable</code>.<br>\n<br>\nThe type of <code class=\"paramref\">value</code> may not directly match <code class=\"paramref\">type</code>, as the type\nis derived from unwrapping nullability and array element types, so use care when looking\nat the value to determine serializability.</p>\n",
      "example": [],
      "overload": {
        "uid": "Xunit.Sdk.IXunitSerializer.IsSerializable*",
        "name": [
          {
            "lang": "csharp",
            "value": "IsSerializable"
          },
          {
            "lang": "vb",
            "value": "IsSerializable"
          }
        ],
        "nameWithType": [
          {
            "lang": "csharp",
            "value": "IXunitSerializer.IsSerializable"
          },
          {
            "lang": "vb",
            "value": "IXunitSerializer.IsSerializable"
          }
        ],
        "fullName": [
          {
            "lang": "csharp",
            "value": "Xunit.Sdk.IXunitSerializer.IsSerializable"
          },
          {
            "lang": "vb",
            "value": "Xunit.Sdk.IXunitSerializer.IsSerializable"
          }
        ],
        "specName": [
          {
            "lang": "csharp",
            "value": "<xref uid=\"Xunit.Sdk.IXunitSerializer.IsSerializable*\" text=\"IsSerializable\"/>"
          },
          {
            "lang": "vb",
            "value": "<xref uid=\"Xunit.Sdk.IXunitSerializer.IsSerializable*\" text=\"IsSerializable\"/>"
          }
        ]
      },
      "level": 0,
      "type": "method",
      "summary": "<p sourcefile=\"v3-2.0.0/common/Xunit.Sdk.IXunitSerializer.yml\" sourcestartlinenumber=\"1\">Determines if a specific value of data is serializable.</p>\n",
      "platform": null
    },
    {
      "uid": "Xunit.Sdk.IXunitSerializer.Serialize(System.Object)",
      "isEii": false,
      "isExtensionMethod": false,
      "parent": "Xunit.Sdk.IXunitSerializer",
      "isExternal": false,
      "name": [
        {
          "lang": "csharp",
          "value": "Serialize(object)"
        },
        {
          "lang": "vb",
          "value": "Serialize(Object)"
        }
      ],
      "nameWithType": [
        {
          "lang": "csharp",
          "value": "IXunitSerializer.Serialize(object)"
        },
        {
          "lang": "vb",
          "value": "IXunitSerializer.Serialize(Object)"
        }
      ],
      "fullName": [
        {
          "lang": "csharp",
          "value": "Xunit.Sdk.IXunitSerializer.Serialize(object)"
        },
        {
          "lang": "vb",
          "value": "Xunit.Sdk.IXunitSerializer.Serialize(Object)"
        }
      ],
      "specName": [
        {
          "lang": "csharp",
          "value": "<xref uid=\"Xunit.Sdk.IXunitSerializer.Serialize(System.Object)\" text=\"Serialize(object)\"/>"
        },
        {
          "lang": "vb",
          "value": "<xref uid=\"Xunit.Sdk.IXunitSerializer.Serialize(System.Object)\" text=\"Serialize(object)\"/>"
        }
      ],
      "syntax": {
        "content": [
          {
            "lang": "csharp",
            "value": "string Serialize(object value)"
          },
          {
            "lang": "vb",
            "value": "Function Serialize(value As Object) As String"
          }
        ],
        "parameters": [
          {
            "id": "value",
            "type": {
              "uid": "System.Object",
              "name": [
                {
                  "lang": "csharp",
                  "value": "object"
                },
                {
                  "lang": "vb",
                  "value": "Object"
                }
              ],
              "nameWithType": [
                {
                  "lang": "csharp",
                  "value": "object"
                },
                {
                  "lang": "vb",
                  "value": "Object"
                }
              ],
              "fullName": [
                {
                  "lang": "csharp",
                  "value": "object"
                },
                {
                  "lang": "vb",
                  "value": "Object"
                }
              ],
              "specName": [
                {
                  "lang": "csharp",
                  "value": "<xref uid=\"System.Object\" text=\"object\"/>"
                },
                {
                  "lang": "vb",
                  "value": "<xref uid=\"System.Object\" text=\"object\"/>"
                }
              ]
            },
            "description": "<p sourcefile=\"v3-2.0.0/common/Xunit.Sdk.IXunitSerializer.yml\" sourcestartlinenumber=\"1\">The value to be serialized</p>\n"
          }
        ],
        "return": {
          "type": {
            "uid": "System.String",
            "name": [
              {
                "lang": "csharp",
                "value": "string"
              },
              {
                "lang": "vb",
                "value": "String"
              }
            ],
            "nameWithType": [
              {
                "lang": "csharp",
                "value": "string"
              },
              {
                "lang": "vb",
                "value": "String"
              }
            ],
            "fullName": [
              {
                "lang": "csharp",
                "value": "string"
              },
              {
                "lang": "vb",
                "value": "String"
              }
            ],
            "specName": [
              {
                "lang": "csharp",
                "value": "<xref uid=\"System.String\" text=\"string\"/>"
              },
              {
                "lang": "vb",
                "value": "<xref uid=\"System.String\" text=\"string\"/>"
              }
            ]
          },
          "description": "<p sourcefile=\"v3-2.0.0/common/Xunit.Sdk.IXunitSerializer.yml\" sourcestartlinenumber=\"1\">The serialized value</p>\n"
        }
      },
      "source": {
        "remote": {
          "path": "src/xunit.v3.common/Abstractions/Serialization/IXunitSerializer.cs",
          "branch": "229879b7653ec0573f36ca4759ccfc915be11a21",
          "repo": "https://github.com/xunit/xunit.git"
        },
        "id": "Serialize",
        "path": "../v3/v3-2.0.0/src/xunit.v3.common/Abstractions/Serialization/IXunitSerializer.cs",
        "startLine": 55,
        "endLine": 0
      },
      "assemblies": [
        "xunit.v3.common"
      ],
      "namespace": "Xunit.Sdk",
      "remarks": "<p sourcefile=\"v3-2.0.0/common/Xunit.Sdk.IXunitSerializer.yml\" sourcestartlinenumber=\"1\">This method will never be called with <code>null</code> values, because those are already\nspecial cased by the serialization system. You may assume that <xref href=\"Xunit.Sdk.IXunitSerializer.IsSerializable(System.Type%2cSystem.Object%2cSystem.String%40)\" data-throw-if-not-resolved=\"false\"></xref>\nis called before this, so any validation done there need not be repeated here.</p>\n",
      "example": [],
      "overload": {
        "uid": "Xunit.Sdk.IXunitSerializer.Serialize*",
        "name": [
          {
            "lang": "csharp",
            "value": "Serialize"
          },
          {
            "lang": "vb",
            "value": "Serialize"
          }
        ],
        "nameWithType": [
          {
            "lang": "csharp",
            "value": "IXunitSerializer.Serialize"
          },
          {
            "lang": "vb",
            "value": "IXunitSerializer.Serialize"
          }
        ],
        "fullName": [
          {
            "lang": "csharp",
            "value": "Xunit.Sdk.IXunitSerializer.Serialize"
          },
          {
            "lang": "vb",
            "value": "Xunit.Sdk.IXunitSerializer.Serialize"
          }
        ],
        "specName": [
          {
            "lang": "csharp",
            "value": "<xref uid=\"Xunit.Sdk.IXunitSerializer.Serialize*\" text=\"Serialize\"/>"
          },
          {
            "lang": "vb",
            "value": "<xref uid=\"Xunit.Sdk.IXunitSerializer.Serialize*\" text=\"Serialize\"/>"
          }
        ]
      },
      "level": 0,
      "type": "method",
      "summary": "<p sourcefile=\"v3-2.0.0/common/Xunit.Sdk.IXunitSerializer.yml\" sourcestartlinenumber=\"1\">Serializes a value into a string to be later deserialized with <xref href=\"Xunit.Sdk.IXunitSerializer.Deserialize(System.Type%2cSystem.String)\" data-throw-if-not-resolved=\"false\"></xref>.</p>\n",
      "platform": null
    }
  ],
  "langs": [
    "csharp",
    "vb"
  ],
  "name": [
    {
      "lang": "csharp",
      "value": "IXunitSerializer"
    },
    {
      "lang": "vb",
      "value": "IXunitSerializer"
    }
  ],
  "nameWithType": [
    {
      "lang": "csharp",
      "value": "IXunitSerializer"
    },
    {
      "lang": "vb",
      "value": "IXunitSerializer"
    }
  ],
  "fullName": [
    {
      "lang": "csharp",
      "value": "Xunit.Sdk.IXunitSerializer"
    },
    {
      "lang": "vb",
      "value": "Xunit.Sdk.IXunitSerializer"
    }
  ],
  "type": "interface",
  "source": {
    "remote": {
      "path": "src/xunit.v3.common/Abstractions/Serialization/IXunitSerializer.cs",
      "branch": "229879b7653ec0573f36ca4759ccfc915be11a21",
      "repo": "https://github.com/xunit/xunit.git"
    },
    "id": "IXunitSerializer",
    "path": "../v3/v3-2.0.0/src/xunit.v3.common/Abstractions/Serialization/IXunitSerializer.cs",
    "startLine": 10,
    "endLine": 0
  },
  "assemblies": [
    "xunit.v3.common"
  ],
  "namespace": {
    "uid": "Xunit.Sdk",
    "isEii": false,
    "isExtensionMethod": false,
    "href": "Xunit.html",
    "name": [
      {
        "lang": "csharp",
        "value": "Xunit.Sdk"
      },
      {
        "lang": "vb",
        "value": "Xunit.Sdk"
      }
    ],
    "nameWithType": [
      {
        "lang": "csharp",
        "value": "Xunit.Sdk"
      },
      {
        "lang": "vb",
        "value": "Xunit.Sdk"
      }
    ],
    "fullName": [
      {
        "lang": "csharp",
        "value": "Xunit.Sdk"
      },
      {
        "lang": "vb",
        "value": "Xunit.Sdk"
      }
    ],
    "specName": [
      {
        "lang": "csharp",
        "value": "<a class=\"xref\" href=\"Xunit.html\">Xunit</a>.<a class=\"xref\" href=\"Xunit.Sdk.html\">Sdk</a>"
      },
      {
        "lang": "vb",
        "value": "<a class=\"xref\" href=\"Xunit.html\">Xunit</a>.<a class=\"xref\" href=\"Xunit.Sdk.html\">Sdk</a>"
      }
    ],
    "level": 0
  },
  "summary": "<p sourcefile=\"v3-2.0.0/common/Xunit.Sdk.IXunitSerializer.yml\" sourcestartlinenumber=\"1\">Implemented by types which can support serialization and deserialization. This\nallows external serializers for types which would be inconvenient or impossible\nto implement <xref href=\"Xunit.Sdk.IXunitSerializable\" data-throw-if-not-resolved=\"false\"></xref> directly.</p>\n",
  "example": [],
  "syntax": {
    "content": [
      {
        "lang": "csharp",
        "value": "public interface IXunitSerializer"
      },
      {
        "lang": "vb",
        "value": "Public Interface IXunitSerializer"
      }
    ]
  },
  "level": 0,
  "extensionMethods": [
    {
      "uid": "System.Object.Xunit.Internal.ObjectExtensions.AsValueTask",
      "isEii": false,
      "isExtensionMethod": false,
      "parent": "Xunit.Internal.ObjectExtensions",
      "definition": "Xunit.Internal.ObjectExtensions.AsValueTask(System.Object)",
      "href": "Xunit.Internal.ObjectExtensions.html#Xunit_Internal_ObjectExtensions_AsValueTask_System_Object_",
      "name": [
        {
          "lang": "csharp",
          "value": "AsValueTask(object)"
        },
        {
          "lang": "vb",
          "value": "AsValueTask(Object)"
        }
      ],
      "nameWithType": [
        {
          "lang": "csharp",
          "value": "ObjectExtensions.AsValueTask(object)"
        },
        {
          "lang": "vb",
          "value": "ObjectExtensions.AsValueTask(Object)"
        }
      ],
      "fullName": [
        {
          "lang": "csharp",
          "value": "Xunit.Internal.ObjectExtensions.AsValueTask(object)"
        },
        {
          "lang": "vb",
          "value": "Xunit.Internal.ObjectExtensions.AsValueTask(Object)"
        }
      ],
      "specName": [
        {
          "lang": "csharp",
          "value": "<a class=\"xref\" href=\"Xunit.Internal.ObjectExtensions.html#Xunit_Internal_ObjectExtensions_AsValueTask_System_Object_\">AsValueTask</a>(<a class=\"xref\" href=\"https://learn.microsoft.com/dotnet/api/system.object\">object</a>)"
        },
        {
          "lang": "vb",
          "value": "<a class=\"xref\" href=\"Xunit.Internal.ObjectExtensions.html#Xunit_Internal_ObjectExtensions_AsValueTask_System_Object_\">AsValueTask</a>(<a class=\"xref\" href=\"https://learn.microsoft.com/dotnet/api/system.object\">Object</a>)"
        }
      ],
      "level": 0
    },
    {
      "uid": "System.Object.Xunit.Internal.ObjectExtensions.ValidateNullablePropertyValue``1(System.Nullable{{T}},System.String)",
      "isEii": false,
      "isExtensionMethod": false,
      "parent": "Xunit.Internal.ObjectExtensions",
      "definition": "Xunit.Internal.ObjectExtensions.ValidateNullablePropertyValue``1(System.Object,System.Nullable{``0},System.String)",
      "href": "Xunit.Internal.ObjectExtensions.html#Xunit_Internal_ObjectExtensions_ValidateNullablePropertyValue__1_System_Object_System_Nullable___0__System_String_",
      "name": [
        {
          "lang": "csharp",
          "value": "ValidateNullablePropertyValue<T>(object, T?, string)"
        },
        {
          "lang": "vb",
          "value": "ValidateNullablePropertyValue(Of T)(Object, T?, String)"
        }
      ],
      "nameWithType": [
        {
          "lang": "csharp",
          "value": "ObjectExtensions.ValidateNullablePropertyValue<T>(object, T?, string)"
        },
        {
          "lang": "vb",
          "value": "ObjectExtensions.ValidateNullablePropertyValue(Of T)(Object, T?, String)"
        }
      ],
      "fullName": [
        {
          "lang": "csharp",
          "value": "Xunit.Internal.ObjectExtensions.ValidateNullablePropertyValue<T>(object, T?, string)"
        },
        {
          "lang": "vb",
          "value": "Xunit.Internal.ObjectExtensions.ValidateNullablePropertyValue(Of T)(Object, T?, String)"
        }
      ],
      "specName": [
        {
          "lang": "csharp",
          "value": "<a class=\"xref\" href=\"Xunit.Internal.ObjectExtensions.html#Xunit_Internal_ObjectExtensions_ValidateNullablePropertyValue__1_System_Object_System_Nullable___0__System_String_\">ValidateNullablePropertyValue</a>&lt;T&gt;(<a class=\"xref\" href=\"https://learn.microsoft.com/dotnet/api/system.object\">object</a>, T?, <a class=\"xref\" href=\"https://learn.microsoft.com/dotnet/api/system.string\">string</a>)"
        },
        {
          "lang": "vb",
          "value": "<a class=\"xref\" href=\"Xunit.Internal.ObjectExtensions.html#Xunit_Internal_ObjectExtensions_ValidateNullablePropertyValue__1_System_Object_System_Nullable___0__System_String_\">ValidateNullablePropertyValue</a>(Of T)(<a class=\"xref\" href=\"https://learn.microsoft.com/dotnet/api/system.object\">Object</a>, T?, <a class=\"xref\" href=\"https://learn.microsoft.com/dotnet/api/system.string\">String</a>)"
        }
      ],
      "level": 0
    },
    {
      "uid": "System.Object.Xunit.Internal.ObjectExtensions.ValidateNullablePropertyValue``1({T},System.String)",
      "isEii": false,
      "isExtensionMethod": false,
      "parent": "Xunit.Internal.ObjectExtensions",
      "definition": "Xunit.Internal.ObjectExtensions.ValidateNullablePropertyValue``1(System.Object,``0,System.String)",
      "href": "Xunit.Internal.ObjectExtensions.html#Xunit_Internal_ObjectExtensions_ValidateNullablePropertyValue__1_System_Object___0_System_String_",
      "name": [
        {
          "lang": "csharp",
          "value": "ValidateNullablePropertyValue<T>(object, T, string)"
        },
        {
          "lang": "vb",
          "value": "ValidateNullablePropertyValue(Of T)(Object, T, String)"
        }
      ],
      "nameWithType": [
        {
          "lang": "csharp",
          "value": "ObjectExtensions.ValidateNullablePropertyValue<T>(object, T, string)"
        },
        {
          "lang": "vb",
          "value": "ObjectExtensions.ValidateNullablePropertyValue(Of T)(Object, T, String)"
        }
      ],
      "fullName": [
        {
          "lang": "csharp",
          "value": "Xunit.Internal.ObjectExtensions.ValidateNullablePropertyValue<T>(object, T, string)"
        },
        {
          "lang": "vb",
          "value": "Xunit.Internal.ObjectExtensions.ValidateNullablePropertyValue(Of T)(Object, T, String)"
        }
      ],
      "specName": [
        {
          "lang": "csharp",
          "value": "<a class=\"xref\" href=\"Xunit.Internal.ObjectExtensions.html#Xunit_Internal_ObjectExtensions_ValidateNullablePropertyValue__1_System_Object___0_System_String_\">ValidateNullablePropertyValue</a>&lt;T&gt;(<a class=\"xref\" href=\"https://learn.microsoft.com/dotnet/api/system.object\">object</a>, T, <a class=\"xref\" href=\"https://learn.microsoft.com/dotnet/api/system.string\">string</a>)"
        },
        {
          "lang": "vb",
          "value": "<a class=\"xref\" href=\"Xunit.Internal.ObjectExtensions.html#Xunit_Internal_ObjectExtensions_ValidateNullablePropertyValue__1_System_Object___0_System_String_\">ValidateNullablePropertyValue</a>(Of T)(<a class=\"xref\" href=\"https://learn.microsoft.com/dotnet/api/system.object\">Object</a>, T, <a class=\"xref\" href=\"https://learn.microsoft.com/dotnet/api/system.string\">String</a>)"
        }
      ],
      "level": 0
    }
  ],
  "_appName": "xunit-proto",
  "_appTitle": "xunit-proto",
  "_enableSearch": true,
  "pdf": false,
  "_systemKeys": [
    "uid",
    "isEii",
    "isExtensionMethod",
    "parent",
    "children",
    "href",
    "langs",
    "name",
    "nameWithType",
    "fullName",
    "type",
    "source",
    "documentation",
    "assemblies",
    "namespace",
    "summary",
    "remarks",
    "example",
    "syntax",
    "overridden",
    "overload",
    "exceptions",
    "seealso",
    "see",
    "inheritance",
    "derivedClasses",
    "level",
    "implements",
    "inheritedMembers",
    "extensionMethods",
    "conceptual",
    "platform",
    "attributes",
    "additionalNotes"
  ],
  "_key": "v3-2.0.0/common/Xunit.Sdk.IXunitSerializer.yml",
  "_navKey": "~/toc.yml",
  "_navPath": "toc.html",
  "_navRel": "../../toc.html",
  "_path": "v3-2.0.0/common/Xunit.Sdk.IXunitSerializer.html",
  "_rel": "../../",
  "_tocKey": "~/v3-2.0.0/common/toc.yml",
  "_tocPath": "v3-2.0.0/common/toc.html",
  "_tocRel": "toc.html",
  "__global": {
    "namespacesInSubtitle": "Namespaces",
    "classesInSubtitle": "Classes",
    "structsInSubtitle": "Structs",
    "interfacesInSubtitle": "Interfaces",
    "enumsInSubtitle": "Enums",
    "delegatesInSubtitle": "Delegates",
    "constructorsInSubtitle": "Constructors",
    "fieldsInSubtitle": "Fields",
    "propertiesInSubtitle": "Properties",
    "methodsInSubtitle": "Methods",
    "eventsInSubtitle": "Events",
    "operatorsInSubtitle": "Operators",
    "eiisInSubtitle": "Explicit Interface Implementations",
    "functionsInSubtitle": "Functions",
    "variablesInSubtitle": "Variables",
    "typeAliasesInSubtitle": "Type Aliases",
    "membersInSubtitle": "Members",
    "improveThisDoc": "Edit this page",
    "viewSource": "View Source",
    "inheritance": "Inheritance",
    "derived": "Derived",
    "inheritedMembers": "Inherited Members",
    "package": "Package",
    "namespace": "Namespace",
    "assembly": "Assembly",
    "syntax": "Syntax",
    "overrides": "Overrides",
    "implements": "Implements",
    "remarks": "Remarks",
    "examples": "Examples",
    "seealso": "See Also",
    "declaration": "Declaration",
    "parameters": "Parameters",
    "typeParameters": "Type Parameters",
    "type": "Type",
    "name": "Name",
    "description": "Description",
    "returns": "Returns",
    "fieldValue": "Field Value",
    "propertyValue": "Property Value",
    "eventType": "Event Type",
    "variableValue": "Variable Value",
    "typeAliasType": "Type Alias Type",
    "exceptions": "Exceptions",
    "condition": "Condition",
    "extensionMethods": "Extension Methods",
    "note": "Note",
    "warning": "Warning",
    "tip": "Tip",
    "important": "Important",
    "caution": "Caution",
    "tocToggleButton": "Show / Hide Table of Contents",
    "tocFilter": "Filter by title",
    "search": "Search",
    "searchResults": "Search Results for",
    "searchResultsCount": "{count} results for \"{query}\"",
    "searchNoResults": "No results for \"{query}\"",
    "pageFirst": "First",
    "pagePrev": "Previous",
    "pageNext": "Next",
    "pageLast": "Last",
    "inThisArticle": "In this article",
    "nextArticle": "Next",
    "prevArticle": "Previous",
    "backToTop": "Back to top",
    "themeLight": "Light",
    "themeDark": "Dark",
    "themeAuto": "Auto",
    "changeTheme": "Change theme",
    "copy": "Copy",
    "downloadPdf": "Download PDF",
    "_shared": {}
  }
}