
{"items":[{"name":"Xunit.Internal","href":"../common/Xunit.Internal.html","topicHref":"../common/Xunit.Internal.html","topicUid":"Xunit.Internal","type":"Namespace","items":[{"name":"CommandLineGroup","href":"Xunit.Internal.CommandLineGroup.html","topicHref":"Xunit.Internal.CommandLineGroup.html","topicUid":"Xunit.Internal.CommandLineGroup","type":"Enum"},{"name":"CommandLineParserBase","href":"Xunit.Internal.CommandLineParserBase.html","topicHref":"Xunit.Internal.CommandLineParserBase.html","topicUid":"Xunit.Internal.CommandLineParserBase","type":"Class"}]},{"name":"Xunit.Runner.Common","href":"Xunit.Runner.Common.html","topicHref":"Xunit.Runner.Common.html","topicUid":"Xunit.Runner.Common","type":"Namespace","items":[{"name":"AfterTestFinished","href":"Xunit.Runner.Common.AfterTestFinished.html","topicHref":"Xunit.Runner.Common.AfterTestFinished.html","topicUid":"Xunit.Runner.Common.AfterTestFinished","type":"Class"},{"name":"AfterTestStarting","href":"Xunit.Runner.Common.AfterTestStarting.html","topicHref":"Xunit.Runner.Common.AfterTestStarting.html","topicUid":"Xunit.Runner.Common.AfterTestStarting","type":"Class"},{"name":"AggregateMessageSink","href":"Xunit.Runner.Common.AggregateMessageSink.html","topicHref":"Xunit.Runner.Common.AggregateMessageSink.html","topicUid":"Xunit.Runner.Common.AggregateMessageSink","type":"Class"},{"name":"AppDomainOption","href":"Xunit.Runner.Common.AppDomainOption.html","topicHref":"Xunit.Runner.Common.AppDomainOption.html","topicUid":"Xunit.Runner.Common.AppDomainOption","type":"Enum"},{"name":"AppDomainSupport","href":"Xunit.Runner.Common.AppDomainSupport.html","topicHref":"Xunit.Runner.Common.AppDomainSupport.html","topicUid":"Xunit.Runner.Common.AppDomainSupport","type":"Enum"},{"name":"AppVeyorReporter","href":"Xunit.Runner.Common.AppVeyorReporter.html","topicHref":"Xunit.Runner.Common.AppVeyorReporter.html","topicUid":"Xunit.Runner.Common.AppVeyorReporter","type":"Class"},{"name":"AppVeyorReporterMessageHandler","href":"Xunit.Runner.Common.AppVeyorReporterMessageHandler.html","topicHref":"Xunit.Runner.Common.AppVeyorReporterMessageHandler.html","topicUid":"Xunit.Runner.Common.AppVeyorReporterMessageHandler","type":"Class"},{"name":"AssemblyMetadata","href":"Xunit.Runner.Common.AssemblyMetadata.html","topicHref":"Xunit.Runner.Common.AssemblyMetadata.html","topicUid":"Xunit.Runner.Common.AssemblyMetadata","type":"Class"},{"name":"BeforeTestFinished","href":"Xunit.Runner.Common.BeforeTestFinished.html","topicHref":"Xunit.Runner.Common.BeforeTestFinished.html","topicUid":"Xunit.Runner.Common.BeforeTestFinished","type":"Class"},{"name":"BeforeTestStarting","href":"Xunit.Runner.Common.BeforeTestStarting.html","topicHref":"Xunit.Runner.Common.BeforeTestStarting.html","topicUid":"Xunit.Runner.Common.BeforeTestStarting","type":"Class"},{"name":"ConfigReader_Json","href":"Xunit.Runner.Common.ConfigReader_Json.html","topicHref":"Xunit.Runner.Common.ConfigReader_Json.html","topicUid":"Xunit.Runner.Common.ConfigReader_Json","type":"Class"},{"name":"ConfigUtility","href":"Xunit.Runner.Common.ConfigUtility.html","topicHref":"Xunit.Runner.Common.ConfigUtility.html","topicUid":"Xunit.Runner.Common.ConfigUtility","type":"Class"},{"name":"ConsoleDiagnosticMessageSink","href":"Xunit.Runner.Common.ConsoleDiagnosticMessageSink.html","topicHref":"Xunit.Runner.Common.ConsoleDiagnosticMessageSink.html","topicUid":"Xunit.Runner.Common.ConsoleDiagnosticMessageSink","type":"Class"},{"name":"ConsoleHelper","href":"Xunit.Runner.Common.ConsoleHelper.html","topicHref":"Xunit.Runner.Common.ConsoleHelper.html","topicUid":"Xunit.Runner.Common.ConsoleHelper","type":"Class"},{"name":"ConsoleProjectLister","href":"Xunit.Runner.Common.ConsoleProjectLister.html","topicHref":"Xunit.Runner.Common.ConsoleProjectLister.html","topicUid":"Xunit.Runner.Common.ConsoleProjectLister","type":"Class"},{"name":"ConsoleRunnerLogger","href":"Xunit.Runner.Common.ConsoleRunnerLogger.html","topicHref":"Xunit.Runner.Common.ConsoleRunnerLogger.html","topicUid":"Xunit.Runner.Common.ConsoleRunnerLogger","type":"Class"},{"name":"DefaultRunnerReporter","href":"Xunit.Runner.Common.DefaultRunnerReporter.html","topicHref":"Xunit.Runner.Common.DefaultRunnerReporter.html","topicUid":"Xunit.Runner.Common.DefaultRunnerReporter","type":"Class"},{"name":"DefaultRunnerReporterMessageHandler","href":"Xunit.Runner.Common.DefaultRunnerReporterMessageHandler.html","topicHref":"Xunit.Runner.Common.DefaultRunnerReporterMessageHandler.html","topicUid":"Xunit.Runner.Common.DefaultRunnerReporterMessageHandler","type":"Class"},{"name":"DiagnosticEventSink","href":"Xunit.Runner.Common.DiagnosticEventSink.html","topicHref":"Xunit.Runner.Common.DiagnosticEventSink.html","topicUid":"Xunit.Runner.Common.DiagnosticEventSink","type":"Class"},{"name":"DiagnosticMessage","href":"Xunit.Runner.Common.DiagnosticMessage.html","topicHref":"Xunit.Runner.Common.DiagnosticMessage.html","topicUid":"Xunit.Runner.Common.DiagnosticMessage","type":"Class"},{"name":"DiscoveryComplete","href":"Xunit.Runner.Common.DiscoveryComplete.html","topicHref":"Xunit.Runner.Common.DiscoveryComplete.html","topicUid":"Xunit.Runner.Common.DiscoveryComplete","type":"Class"},{"name":"DiscoveryEventSink","href":"Xunit.Runner.Common.DiscoveryEventSink.html","topicHref":"Xunit.Runner.Common.DiscoveryEventSink.html","topicUid":"Xunit.Runner.Common.DiscoveryEventSink","type":"Class"},{"name":"DiscoveryStarting","href":"Xunit.Runner.Common.DiscoveryStarting.html","topicHref":"Xunit.Runner.Common.DiscoveryStarting.html","topicUid":"Xunit.Runner.Common.DiscoveryStarting","type":"Class"},{"name":"ErrorMessage","href":"Xunit.Runner.Common.ErrorMessage.html","topicHref":"Xunit.Runner.Common.ErrorMessage.html","topicUid":"Xunit.Runner.Common.ErrorMessage","type":"Class"},{"name":"ExecutionEventSink","href":"Xunit.Runner.Common.ExecutionEventSink.html","topicHref":"Xunit.Runner.Common.ExecutionEventSink.html","topicUid":"Xunit.Runner.Common.ExecutionEventSink","type":"Class"},{"name":"ExecutionSink","href":"Xunit.Runner.Common.ExecutionSink.html","topicHref":"Xunit.Runner.Common.ExecutionSink.html","topicUid":"Xunit.Runner.Common.ExecutionSink","type":"Class"},{"name":"ExecutionSinkOptions","href":"Xunit.Runner.Common.ExecutionSinkOptions.html","topicHref":"Xunit.Runner.Common.ExecutionSinkOptions.html","topicUid":"Xunit.Runner.Common.ExecutionSinkOptions","type":"Class"},{"name":"ExecutionSummary","href":"Xunit.Runner.Common.ExecutionSummary.html","topicHref":"Xunit.Runner.Common.ExecutionSummary.html","topicUid":"Xunit.Runner.Common.ExecutionSummary","type":"Class"},{"name":"IRegisterRunnerReporterAttribute","href":"Xunit.Runner.Common.IRegisterRunnerReporterAttribute.html","topicHref":"Xunit.Runner.Common.IRegisterRunnerReporterAttribute.html","topicUid":"Xunit.Runner.Common.IRegisterRunnerReporterAttribute","type":"Interface"},{"name":"IRunnerLogger","href":"Xunit.Runner.Common.IRunnerLogger.html","topicHref":"Xunit.Runner.Common.IRunnerLogger.html","topicUid":"Xunit.Runner.Common.IRunnerLogger","type":"Interface"},{"name":"IRunnerLoggerExtensions","href":"Xunit.Runner.Common.IRunnerLoggerExtensions.html","topicHref":"Xunit.Runner.Common.IRunnerLoggerExtensions.html","topicUid":"Xunit.Runner.Common.IRunnerLoggerExtensions","type":"Class"},{"name":"IRunnerReporter","href":"Xunit.Runner.Common.IRunnerReporter.html","topicHref":"Xunit.Runner.Common.IRunnerReporter.html","topicUid":"Xunit.Runner.Common.IRunnerReporter","type":"Interface"},{"name":"IRunnerReporterMessageHandler","href":"Xunit.Runner.Common.IRunnerReporterMessageHandler.html","topicHref":"Xunit.Runner.Common.IRunnerReporterMessageHandler.html","topicUid":"Xunit.Runner.Common.IRunnerReporterMessageHandler","type":"Interface"},{"name":"ISourceInformationProvider","href":"Xunit.Runner.Common.ISourceInformationProvider.html","topicHref":"Xunit.Runner.Common.ISourceInformationProvider.html","topicUid":"Xunit.Runner.Common.ISourceInformationProvider","type":"Interface"},{"name":"ITestCaseFilter","href":"Xunit.Runner.Common.ITestCaseFilter.html","topicHref":"Xunit.Runner.Common.ITestCaseFilter.html","topicUid":"Xunit.Runner.Common.ITestCaseFilter","type":"Interface"},{"name":"InternalDiagnosticMessage","href":"Xunit.Runner.Common.InternalDiagnosticMessage.html","topicHref":"Xunit.Runner.Common.InternalDiagnosticMessage.html","topicUid":"Xunit.Runner.Common.InternalDiagnosticMessage","type":"Class"},{"name":"JsonReporter","href":"Xunit.Runner.Common.JsonReporter.html","topicHref":"Xunit.Runner.Common.JsonReporter.html","topicUid":"Xunit.Runner.Common.JsonReporter","type":"Class"},{"name":"JsonReporterMessageHandler","href":"Xunit.Runner.Common.JsonReporterMessageHandler.html","topicHref":"Xunit.Runner.Common.JsonReporterMessageHandler.html","topicUid":"Xunit.Runner.Common.JsonReporterMessageHandler","type":"Class"},{"name":"ListFormat","href":"Xunit.Runner.Common.ListFormat.html","topicHref":"Xunit.Runner.Common.ListFormat.html","topicUid":"Xunit.Runner.Common.ListFormat","type":"Enum"},{"name":"ListOption","href":"Xunit.Runner.Common.ListOption.html","topicHref":"Xunit.Runner.Common.ListOption.html","topicUid":"Xunit.Runner.Common.ListOption","type":"Enum"},{"name":"LongRunningTestsSummary","href":"Xunit.Runner.Common.LongRunningTestsSummary.html","topicHref":"Xunit.Runner.Common.LongRunningTestsSummary.html","topicUid":"Xunit.Runner.Common.LongRunningTestsSummary","type":"Class"},{"name":"MessageHandlerArgs","href":"Xunit.Runner.Common.MessageHandlerArgs.html","topicHref":"Xunit.Runner.Common.MessageHandlerArgs.html","topicUid":"Xunit.Runner.Common.MessageHandlerArgs","type":"Class"},{"name":"MessageHandlerArgs<TMessage>","href":"Xunit.Runner.Common.MessageHandlerArgs-1.html","topicHref":"Xunit.Runner.Common.MessageHandlerArgs-1.html","topicUid":"Xunit.Runner.Common.MessageHandlerArgs`1","type":"Class"},{"name":"MessageHandler<TMessage>","href":"Xunit.Runner.Common.MessageHandler-1.html","topicHref":"Xunit.Runner.Common.MessageHandler-1.html","topicUid":"Xunit.Runner.Common.MessageHandler`1","type":"Delegate"},{"name":"MessageMetadataCache","href":"Xunit.Runner.Common.MessageMetadataCache.html","topicHref":"Xunit.Runner.Common.MessageMetadataCache.html","topicUid":"Xunit.Runner.Common.MessageMetadataCache","type":"Class"},{"name":"MessageSinkMessage","href":"Xunit.Runner.Common.MessageSinkMessage.html","topicHref":"Xunit.Runner.Common.MessageSinkMessage.html","topicUid":"Xunit.Runner.Common.MessageSinkMessage","type":"Class"},{"name":"MessageSinkMessageDeserializer","href":"Xunit.Runner.Common.MessageSinkMessageDeserializer.html","topicHref":"Xunit.Runner.Common.MessageSinkMessageDeserializer.html","topicUid":"Xunit.Runner.Common.MessageSinkMessageDeserializer","type":"Class"},{"name":"NullSourceInformationProvider","href":"Xunit.Runner.Common.NullSourceInformationProvider.html","topicHref":"Xunit.Runner.Common.NullSourceInformationProvider.html","topicUid":"Xunit.Runner.Common.NullSourceInformationProvider","type":"Class"},{"name":"ParallelismOption","href":"Xunit.Runner.Common.ParallelismOption.html","topicHref":"Xunit.Runner.Common.ParallelismOption.html","topicUid":"Xunit.Runner.Common.ParallelismOption","type":"Enum"},{"name":"QueryFilterParser","href":"Xunit.Runner.Common.QueryFilterParser.html","topicHref":"Xunit.Runner.Common.QueryFilterParser.html","topicUid":"Xunit.Runner.Common.QueryFilterParser","type":"Class"},{"name":"QuietReporter","href":"Xunit.Runner.Common.QuietReporter.html","topicHref":"Xunit.Runner.Common.QuietReporter.html","topicUid":"Xunit.Runner.Common.QuietReporter","type":"Class"},{"name":"QuietReporterMessageHandler","href":"Xunit.Runner.Common.QuietReporterMessageHandler.html","topicHref":"Xunit.Runner.Common.QuietReporterMessageHandler.html","topicUid":"Xunit.Runner.Common.QuietReporterMessageHandler","type":"Class"},{"name":"RegisterRunnerReporterAttribute","href":"Xunit.Runner.Common.RegisterRunnerReporterAttribute.html","topicHref":"Xunit.Runner.Common.RegisterRunnerReporterAttribute.html","topicUid":"Xunit.Runner.Common.RegisterRunnerReporterAttribute","type":"Class"},{"name":"RegisteredRunnerReporters","href":"Xunit.Runner.Common.RegisteredRunnerReporters.html","topicHref":"Xunit.Runner.Common.RegisteredRunnerReporters.html","topicUid":"Xunit.Runner.Common.RegisteredRunnerReporters","type":"Class"},{"name":"RunnerEventSink","href":"Xunit.Runner.Common.RunnerEventSink.html","topicHref":"Xunit.Runner.Common.RunnerEventSink.html","topicUid":"Xunit.Runner.Common.RunnerEventSink","type":"Class"},{"name":"SilentReporter","href":"Xunit.Runner.Common.SilentReporter.html","topicHref":"Xunit.Runner.Common.SilentReporter.html","topicUid":"Xunit.Runner.Common.SilentReporter","type":"Class"},{"name":"SilentReporterMessageHandler","href":"Xunit.Runner.Common.SilentReporterMessageHandler.html","topicHref":"Xunit.Runner.Common.SilentReporterMessageHandler.html","topicUid":"Xunit.Runner.Common.SilentReporterMessageHandler","type":"Class"},{"name":"SourceInformation","href":"Xunit.Runner.Common.SourceInformation.html","topicHref":"Xunit.Runner.Common.SourceInformation.html","topicUid":"Xunit.Runner.Common.SourceInformation","type":"Struct"},{"name":"StackFrameInfo","href":"Xunit.Runner.Common.StackFrameInfo.html","topicHref":"Xunit.Runner.Common.StackFrameInfo.html","topicUid":"Xunit.Runner.Common.StackFrameInfo","type":"Struct"},{"name":"StackFrameTransformer","href":"Xunit.Runner.Common.StackFrameTransformer.html","topicHref":"Xunit.Runner.Common.StackFrameTransformer.html","topicUid":"Xunit.Runner.Common.StackFrameTransformer","type":"Class"},{"name":"TargetFrameworkIdentifier","href":"Xunit.Runner.Common.TargetFrameworkIdentifier.html","topicHref":"Xunit.Runner.Common.TargetFrameworkIdentifier.html","topicUid":"Xunit.Runner.Common.TargetFrameworkIdentifier","type":"Enum"},{"name":"TeamCityReporter","href":"Xunit.Runner.Common.TeamCityReporter.html","topicHref":"Xunit.Runner.Common.TeamCityReporter.html","topicUid":"Xunit.Runner.Common.TeamCityReporter","type":"Class"},{"name":"TeamCityReporterMessageHandler","href":"Xunit.Runner.Common.TeamCityReporterMessageHandler.html","topicHref":"Xunit.Runner.Common.TeamCityReporterMessageHandler.html","topicUid":"Xunit.Runner.Common.TeamCityReporterMessageHandler","type":"Class"},{"name":"TestAssemblyCleanupFailure","href":"Xunit.Runner.Common.TestAssemblyCleanupFailure.html","topicHref":"Xunit.Runner.Common.TestAssemblyCleanupFailure.html","topicUid":"Xunit.Runner.Common.TestAssemblyCleanupFailure","type":"Class"},{"name":"TestAssemblyConfiguration","href":"Xunit.Runner.Common.TestAssemblyConfiguration.html","topicHref":"Xunit.Runner.Common.TestAssemblyConfiguration.html","topicUid":"Xunit.Runner.Common.TestAssemblyConfiguration","type":"Class"},{"name":"TestAssemblyDiscoveryFinished","href":"Xunit.Runner.Common.TestAssemblyDiscoveryFinished.html","topicHref":"Xunit.Runner.Common.TestAssemblyDiscoveryFinished.html","topicUid":"Xunit.Runner.Common.TestAssemblyDiscoveryFinished","type":"Class"},{"name":"TestAssemblyDiscoveryStarting","href":"Xunit.Runner.Common.TestAssemblyDiscoveryStarting.html","topicHref":"Xunit.Runner.Common.TestAssemblyDiscoveryStarting.html","topicUid":"Xunit.Runner.Common.TestAssemblyDiscoveryStarting","type":"Class"},{"name":"TestAssemblyExecutionFinished","href":"Xunit.Runner.Common.TestAssemblyExecutionFinished.html","topicHref":"Xunit.Runner.Common.TestAssemblyExecutionFinished.html","topicUid":"Xunit.Runner.Common.TestAssemblyExecutionFinished","type":"Class"},{"name":"TestAssemblyExecutionStarting","href":"Xunit.Runner.Common.TestAssemblyExecutionStarting.html","topicHref":"Xunit.Runner.Common.TestAssemblyExecutionStarting.html","topicUid":"Xunit.Runner.Common.TestAssemblyExecutionStarting","type":"Class"},{"name":"TestAssemblyFinished","href":"Xunit.Runner.Common.TestAssemblyFinished.html","topicHref":"Xunit.Runner.Common.TestAssemblyFinished.html","topicUid":"Xunit.Runner.Common.TestAssemblyFinished","type":"Class"},{"name":"TestAssemblyMessage","href":"Xunit.Runner.Common.TestAssemblyMessage.html","topicHref":"Xunit.Runner.Common.TestAssemblyMessage.html","topicUid":"Xunit.Runner.Common.TestAssemblyMessage","type":"Class"},{"name":"TestAssemblyStarting","href":"Xunit.Runner.Common.TestAssemblyStarting.html","topicHref":"Xunit.Runner.Common.TestAssemblyStarting.html","topicUid":"Xunit.Runner.Common.TestAssemblyStarting","type":"Class"},{"name":"TestCaseCleanupFailure","href":"Xunit.Runner.Common.TestCaseCleanupFailure.html","topicHref":"Xunit.Runner.Common.TestCaseCleanupFailure.html","topicUid":"Xunit.Runner.Common.TestCaseCleanupFailure","type":"Class"},{"name":"TestCaseDiscovered","href":"Xunit.Runner.Common.TestCaseDiscovered.html","topicHref":"Xunit.Runner.Common.TestCaseDiscovered.html","topicUid":"Xunit.Runner.Common.TestCaseDiscovered","type":"Class"},{"name":"TestCaseFinished","href":"Xunit.Runner.Common.TestCaseFinished.html","topicHref":"Xunit.Runner.Common.TestCaseFinished.html","topicUid":"Xunit.Runner.Common.TestCaseFinished","type":"Class"},{"name":"TestCaseMessage","href":"Xunit.Runner.Common.TestCaseMessage.html","topicHref":"Xunit.Runner.Common.TestCaseMessage.html","topicUid":"Xunit.Runner.Common.TestCaseMessage","type":"Class"},{"name":"TestCaseStarting","href":"Xunit.Runner.Common.TestCaseStarting.html","topicHref":"Xunit.Runner.Common.TestCaseStarting.html","topicUid":"Xunit.Runner.Common.TestCaseStarting","type":"Class"},{"name":"TestClassCleanupFailure","href":"Xunit.Runner.Common.TestClassCleanupFailure.html","topicHref":"Xunit.Runner.Common.TestClassCleanupFailure.html","topicUid":"Xunit.Runner.Common.TestClassCleanupFailure","type":"Class"},{"name":"TestClassConstructionFinished","href":"Xunit.Runner.Common.TestClassConstructionFinished.html","topicHref":"Xunit.Runner.Common.TestClassConstructionFinished.html","topicUid":"Xunit.Runner.Common.TestClassConstructionFinished","type":"Class"},{"name":"TestClassConstructionStarting","href":"Xunit.Runner.Common.TestClassConstructionStarting.html","topicHref":"Xunit.Runner.Common.TestClassConstructionStarting.html","topicUid":"Xunit.Runner.Common.TestClassConstructionStarting","type":"Class"},{"name":"TestClassDisposeFinished","href":"Xunit.Runner.Common.TestClassDisposeFinished.html","topicHref":"Xunit.Runner.Common.TestClassDisposeFinished.html","topicUid":"Xunit.Runner.Common.TestClassDisposeFinished","type":"Class"},{"name":"TestClassDisposeStarting","href":"Xunit.Runner.Common.TestClassDisposeStarting.html","topicHref":"Xunit.Runner.Common.TestClassDisposeStarting.html","topicUid":"Xunit.Runner.Common.TestClassDisposeStarting","type":"Class"},{"name":"TestClassFinished","href":"Xunit.Runner.Common.TestClassFinished.html","topicHref":"Xunit.Runner.Common.TestClassFinished.html","topicUid":"Xunit.Runner.Common.TestClassFinished","type":"Class"},{"name":"TestClassMessage","href":"Xunit.Runner.Common.TestClassMessage.html","topicHref":"Xunit.Runner.Common.TestClassMessage.html","topicUid":"Xunit.Runner.Common.TestClassMessage","type":"Class"},{"name":"TestClassStarting","href":"Xunit.Runner.Common.TestClassStarting.html","topicHref":"Xunit.Runner.Common.TestClassStarting.html","topicUid":"Xunit.Runner.Common.TestClassStarting","type":"Class"},{"name":"TestCleanupFailure","href":"Xunit.Runner.Common.TestCleanupFailure.html","topicHref":"Xunit.Runner.Common.TestCleanupFailure.html","topicUid":"Xunit.Runner.Common.TestCleanupFailure","type":"Class"},{"name":"TestCollectionCleanupFailure","href":"Xunit.Runner.Common.TestCollectionCleanupFailure.html","topicHref":"Xunit.Runner.Common.TestCollectionCleanupFailure.html","topicUid":"Xunit.Runner.Common.TestCollectionCleanupFailure","type":"Class"},{"name":"TestCollectionFinished","href":"Xunit.Runner.Common.TestCollectionFinished.html","topicHref":"Xunit.Runner.Common.TestCollectionFinished.html","topicUid":"Xunit.Runner.Common.TestCollectionFinished","type":"Class"},{"name":"TestCollectionMessage","href":"Xunit.Runner.Common.TestCollectionMessage.html","topicHref":"Xunit.Runner.Common.TestCollectionMessage.html","topicUid":"Xunit.Runner.Common.TestCollectionMessage","type":"Class"},{"name":"TestCollectionStarting","href":"Xunit.Runner.Common.TestCollectionStarting.html","topicHref":"Xunit.Runner.Common.TestCollectionStarting.html","topicUid":"Xunit.Runner.Common.TestCollectionStarting","type":"Class"},{"name":"TestDiscoverySink","href":"Xunit.Runner.Common.TestDiscoverySink.html","topicHref":"Xunit.Runner.Common.TestDiscoverySink.html","topicUid":"Xunit.Runner.Common.TestDiscoverySink","type":"Class"},{"name":"TestExecutionSummaries","href":"Xunit.Runner.Common.TestExecutionSummaries.html","topicHref":"Xunit.Runner.Common.TestExecutionSummaries.html","topicUid":"Xunit.Runner.Common.TestExecutionSummaries","type":"Class"},{"name":"TestFailed","href":"Xunit.Runner.Common.TestFailed.html","topicHref":"Xunit.Runner.Common.TestFailed.html","topicUid":"Xunit.Runner.Common.TestFailed","type":"Class"},{"name":"TestFinished","href":"Xunit.Runner.Common.TestFinished.html","topicHref":"Xunit.Runner.Common.TestFinished.html","topicUid":"Xunit.Runner.Common.TestFinished","type":"Class"},{"name":"TestFrameworkOptions","href":"Xunit.Runner.Common.TestFrameworkOptions.html","topicHref":"Xunit.Runner.Common.TestFrameworkOptions.html","topicUid":"Xunit.Runner.Common.TestFrameworkOptions","type":"Class"},{"name":"TestMessage","href":"Xunit.Runner.Common.TestMessage.html","topicHref":"Xunit.Runner.Common.TestMessage.html","topicUid":"Xunit.Runner.Common.TestMessage","type":"Class"},{"name":"TestMessageSink","href":"Xunit.Runner.Common.TestMessageSink.html","topicHref":"Xunit.Runner.Common.TestMessageSink.html","topicUid":"Xunit.Runner.Common.TestMessageSink","type":"Class"},{"name":"TestMethodCleanupFailure","href":"Xunit.Runner.Common.TestMethodCleanupFailure.html","topicHref":"Xunit.Runner.Common.TestMethodCleanupFailure.html","topicUid":"Xunit.Runner.Common.TestMethodCleanupFailure","type":"Class"},{"name":"TestMethodFinished","href":"Xunit.Runner.Common.TestMethodFinished.html","topicHref":"Xunit.Runner.Common.TestMethodFinished.html","topicUid":"Xunit.Runner.Common.TestMethodFinished","type":"Class"},{"name":"TestMethodMessage","href":"Xunit.Runner.Common.TestMethodMessage.html","topicHref":"Xunit.Runner.Common.TestMethodMessage.html","topicUid":"Xunit.Runner.Common.TestMethodMessage","type":"Class"},{"name":"TestMethodStarting","href":"Xunit.Runner.Common.TestMethodStarting.html","topicHref":"Xunit.Runner.Common.TestMethodStarting.html","topicUid":"Xunit.Runner.Common.TestMethodStarting","type":"Class"},{"name":"TestNotRun","href":"Xunit.Runner.Common.TestNotRun.html","topicHref":"Xunit.Runner.Common.TestNotRun.html","topicUid":"Xunit.Runner.Common.TestNotRun","type":"Class"},{"name":"TestOutput","href":"Xunit.Runner.Common.TestOutput.html","topicHref":"Xunit.Runner.Common.TestOutput.html","topicUid":"Xunit.Runner.Common.TestOutput","type":"Class"},{"name":"TestPassed","href":"Xunit.Runner.Common.TestPassed.html","topicHref":"Xunit.Runner.Common.TestPassed.html","topicUid":"Xunit.Runner.Common.TestPassed","type":"Class"},{"name":"TestProjectConfiguration","href":"Xunit.Runner.Common.TestProjectConfiguration.html","topicHref":"Xunit.Runner.Common.TestProjectConfiguration.html","topicUid":"Xunit.Runner.Common.TestProjectConfiguration","type":"Class"},{"name":"TestResultMessage","href":"Xunit.Runner.Common.TestResultMessage.html","topicHref":"Xunit.Runner.Common.TestResultMessage.html","topicUid":"Xunit.Runner.Common.TestResultMessage","type":"Class"},{"name":"TestSkipped","href":"Xunit.Runner.Common.TestSkipped.html","topicHref":"Xunit.Runner.Common.TestSkipped.html","topicUid":"Xunit.Runner.Common.TestSkipped","type":"Class"},{"name":"TestStarting","href":"Xunit.Runner.Common.TestStarting.html","topicHref":"Xunit.Runner.Common.TestStarting.html","topicUid":"Xunit.Runner.Common.TestStarting","type":"Class"},{"name":"Transform","href":"Xunit.Runner.Common.Transform.html","topicHref":"Xunit.Runner.Common.Transform.html","topicUid":"Xunit.Runner.Common.Transform","type":"Class"},{"name":"TransformFactory","href":"Xunit.Runner.Common.TransformFactory.html","topicHref":"Xunit.Runner.Common.TransformFactory.html","topicUid":"Xunit.Runner.Common.TransformFactory","type":"Class"},{"name":"VerboseReporter","href":"Xunit.Runner.Common.VerboseReporter.html","topicHref":"Xunit.Runner.Common.VerboseReporter.html","topicUid":"Xunit.Runner.Common.VerboseReporter","type":"Class"},{"name":"VerboseReporterMessageHandler","href":"Xunit.Runner.Common.VerboseReporterMessageHandler.html","topicHref":"Xunit.Runner.Common.VerboseReporterMessageHandler.html","topicUid":"Xunit.Runner.Common.VerboseReporterMessageHandler","type":"Class"},{"name":"VstsReporter","href":"Xunit.Runner.Common.VstsReporter.html","topicHref":"Xunit.Runner.Common.VstsReporter.html","topicUid":"Xunit.Runner.Common.VstsReporter","type":"Class"},{"name":"VstsReporterMessageHandler","href":"Xunit.Runner.Common.VstsReporterMessageHandler.html","topicHref":"Xunit.Runner.Common.VstsReporterMessageHandler.html","topicUid":"Xunit.Runner.Common.VstsReporterMessageHandler","type":"Class"},{"name":"XunitFilters","href":"Xunit.Runner.Common.XunitFilters.html","topicHref":"Xunit.Runner.Common.XunitFilters.html","topicUid":"Xunit.Runner.Common.XunitFilters","type":"Class"},{"name":"XunitProject","href":"Xunit.Runner.Common.XunitProject.html","topicHref":"Xunit.Runner.Common.XunitProject.html","topicUid":"Xunit.Runner.Common.XunitProject","type":"Class"},{"name":"XunitProjectAssembly","href":"Xunit.Runner.Common.XunitProjectAssembly.html","topicHref":"Xunit.Runner.Common.XunitProjectAssembly.html","topicUid":"Xunit.Runner.Common.XunitProjectAssembly","type":"Class"}]},{"name":"Xunit.Sdk","href":"../assert/Xunit.Sdk.html","topicHref":"../assert/Xunit.Sdk.html","topicUid":"Xunit.Sdk","type":"Namespace","items":[{"name":"MessageSinkMessageExtensions","href":"Xunit.Sdk.MessageSinkMessageExtensions.html","topicHref":"Xunit.Sdk.MessageSinkMessageExtensions.html","topicUid":"Xunit.Sdk.MessageSinkMessageExtensions","type":"Class"},{"name":"TestFrameworkOptionsReadWriteExtensions","href":"Xunit.Sdk.TestFrameworkOptionsReadWriteExtensions.html","topicHref":"Xunit.Sdk.TestFrameworkOptionsReadWriteExtensions.html","topicUid":"Xunit.Sdk.TestFrameworkOptionsReadWriteExtensions","type":"Class"}]}],"memberLayout":"SamePage","pdf":false}
